iot_daemonize/__init__.py
iot_daemonize/__version__.py
iot_daemonize/configuration.py
iot_daemonize/daemonize.py
iot_daemonize/http.py
iot_daemonize/mqtt.py
iot_daemonize-0.1.0.dist-info/licenses/LICENSE.md
iot_daemonize-0.1.0.dist-info/METADATA
iot_daemonize-0.1.0.dist-info/WHEEL
iot_daemonize-0.1.0.dist-info/top_level.txt
iot_daemonize-0.1.0.dist-info/RECORD
