Metadata-Version: 2.4
Name: iot-daemonize
Version: 0.1.0
Summary: A small framework for IOT xyz2mqtt daemons
Author-email: Gerrit Beine <mail@gerritbeine.com>
Maintainer-email: Gerrit Beine <mail@gerritbeine.com>
License: Copyright (c) 2016-2025, Gerrit Beine
Project-URL: Homepage, https://c0d3.sh/smarthome/python-iot-daemonize
Classifier: Development Status :: 4 - Beta
Classifier: Intended Audience :: Developers
Classifier: License :: OSI Approved :: BSD License
Classifier: Programming Language :: Python :: 3.8
Classifier: Topic :: Home Automation
Requires-Python: >=3.8
License-File: LICENSE.md
Requires-Dist: bottle
Requires-Dist: paho-mqtt
Dynamic: license-file
